muzak/__init__.py
muzak/__main__.py
muzak/cli/__init__.py
muzak/cli/__main__.py
muzak/drivers/__init__.py
muzak/drivers/errors.py
muzak/drivers/parser/__init__.py
muzak/drivers/parser/tokens.py
muzak/tools/__init__.py
muzak/utilities/__init__.py
muzak/utilities/decorators.py
muzak/utilities/rpc.py
muzak-0.8.3.dist-info/LICENSE
muzak-0.8.3.dist-info/METADATA
muzak-0.8.3.dist-info/WHEEL
muzak-0.8.3.dist-info/entry_points.txt
muzak-0.8.3.dist-info/top_level.txt
muzak-0.8.3.dist-info/RECORD
